flask_injector/__init__.py
flask_injector/py.typed
flask_injector/tests.py
Flask_Injector-0.15.0.dist-info/COPYING
Flask_Injector-0.15.0.dist-info/METADATA
Flask_Injector-0.15.0.dist-info/WHEEL
Flask_Injector-0.15.0.dist-info/top_level.txt
Flask_Injector-0.15.0.dist-info/zip-safe
Flask_Injector-0.15.0.dist-info/RECORD
