Metadata-Version: 2.1
Name: Flask-Injector
Version: 0.15.0
Summary: Adds Injector, a Dependency Injection framework, support to Flask.
Home-page: https://github.com/alecthomas/flask_injector
Author: Alec Thomas
Author-email: alec@swapoff.org
License: BSD
Keywords: Dependency Injection,Flask
Platform: any
Classifier: Development Status :: 5 - Production/Stable
Classifier: Intended Audience :: Developers
Classifier: License :: OSI Approved :: MIT License
Classifier: Operating System :: OS Independent
Classifier: Topic :: Software Development :: Testing
Classifier: Topic :: Software Development :: Libraries
Classifier: Topic :: Utilities
Classifier: Framework :: Flask
Classifier: Programming Language :: Python
Classifier: Programming Language :: Python :: 3
Classifier: Programming Language :: Python :: 3.7
Classifier: Programming Language :: Python :: 3.8
Classifier: Programming Language :: Python :: 3.9
Classifier: Programming Language :: Python :: 3.10
Classifier: Programming Language :: Python :: Implementation :: CPython
License-File: COPYING
